README.rst
setup.py
mycode/__init__.py
nose_mycode.egg-info/PKG-INFO
nose_mycode.egg-info/SOURCES.txt
nose_mycode.egg-info/dependency_links.txt
nose_mycode.egg-info/entry_points.txt
nose_mycode.egg-info/not-zip-safe
nose_mycode.egg-info/top_level.txt