Metadata-Version: 1.0
Name: nose-mycode
Version: 0.0.3
Summary: Produces a colour coded nose stack trace
Home-page: https://github.com/nose-my-code/nose-my-code
Author: Hansel Dunlop, Jarek Dziedzic, Greg Loyse, Tina Zhang
Author-email: aychedee@github.com, jarekdziedzic@github.com, arachnegl@github.com, ttz21@github.com
License: BSD
Platform: UNKNOWN
